jl/__init__.py
jl/__version__.py
jl/dump.py
jl/load.py
jl-0.0.3.dist-info/LICENSE
jl-0.0.3.dist-info/METADATA
jl-0.0.3.dist-info/WHEEL
jl-0.0.3.dist-info/top_level.txt
jl-0.0.3.dist-info/zip-safe
jl-0.0.3.dist-info/RECORD
